tUilKit/__init__.py
tUilKit/factories.py
tUilKit/config/BORDER_PATTERNS.json
tUilKit/config/COLOURS.json
tUilKit/config/COLUMN_MAPPING.json
tUilKit/config/GLOBAL_CONFIG.json
tUilKit/config/__init__.py
tUilKit/config/config.py
tUilKit/dict/DICT_CODES.py
tUilKit/dict/DICT_COLOURS.py
tUilKit/dict/__init__.py
tUilKit/interfaces/colour_interface.py
tUilKit/interfaces/config_loader_interface.py
tUilKit/interfaces/df_interface.py
tUilKit/interfaces/file_system_interface.py
tUilKit/interfaces/logger_interface.py
tUilKit/utils/__init__.py
tUilKit/utils/formatter.py
tUilKit/utils/fs.py
tUilKit/utils/output.py
tUilKit/utils/sheets.py
tuilkit-0.8.1.dist-info/licenses/LICENSE
tuilkit-0.8.1.dist-info/METADATA
tuilkit-0.8.1.dist-info/WHEEL
tuilkit-0.8.1.dist-info/top_level.txt
tuilkit-0.8.1.dist-info/RECORD
