Metadata-Version: 2.4
Name: tUilKit
Version: 0.8.1
Summary: A modular Python toolkit providing utility functions, dictionaries, and configuration for development projects, structured around interfaces.
Home-page: https://pypi.org/project/tUilKit/
Author: Daniel Austin
Author-email: Daniel Austin <the.potato.gnome@gmail.com>
License: MIT License
Project-URL: Homepage, https://pypi.org/project/tUilKit/
Project-URL: Repository, https://github.com/potatognome/tUilKit
Classifier: Programming Language :: Python :: 3
Classifier: License :: OSI Approved :: MIT License
Classifier: Operating System :: OS Independent
Requires-Python: >=3.7
License-File: LICENSE
Requires-Dist: pandas
Requires-Dist: fuzzywuzzy
Requires-Dist: pyyaml
Dynamic: author
Dynamic: home-page
Dynamic: license-file
Dynamic: requires-python
